koussi/__init__.py
koussi/secrets.py
test/TestSecrets.py
test/__init__.py
koussi-0.0.9.dist-info/METADATA
koussi-0.0.9.dist-info/WHEEL
koussi-0.0.9.dist-info/top_level.txt
koussi-0.0.9.dist-info/RECORD
