Metadata-Version: 2.1
Name: koussi
Version: 0.0.9
Summary: Secrets koussi
Home-page: https://github.com/pavelch/koussi
Author: Pavel Chernovsky
Author-email: pchernovsky@gmail.com
License: UNKNOWN
Platform: UNKNOWN
Classifier: Programming Language :: Python :: 3
Classifier: License :: OSI Approved :: MIT License
Classifier: Operating System :: OS Independent
Requires-Python: >=3.6
Requires-Dist: certifi
Requires-Dist: ruamel.yaml
